Metadata-Version: 2.4
Name: redgit
Version: 1.3.3
Summary: AI-powered Git workflow assistant with task management integration
Author-email: Your Name <your.email@example.com>
License-Expression: MIT
Project-URL: Homepage, https://github.com/ertiz82/redgit
Project-URL: Documentation, https://github.com/ertiz82/redgit#readme
Project-URL: Repository, https://github.com/ertiz82/redgit.git
Project-URL: Issues, https://github.com/ertiz82/redgit/issues
Keywords: git,commit,ai,jira,automation,workflow,task-management
Classifier: Development Status :: 4 - Beta
Classifier: Environment :: Console
Classifier: Intended Audience :: Developers
Classifier: Operating System :: OS Independent
Classifier: Programming Language :: Python :: 3
Classifier: Programming Language :: Python :: 3.9
Classifier: Programming Language :: Python :: 3.10
Classifier: Programming Language :: Python :: 3.11
Classifier: Programming Language :: Python :: 3.12
Classifier: Programming Language :: Python :: 3.13
Classifier: Programming Language :: Python :: 3.14
Classifier: Topic :: Software Development :: Version Control :: Git
Classifier: Topic :: Software Development :: Build Tools
Requires-Python: >=3.9
License-File: LICENSE
Requires-Dist: typer>=0.12.0
Requires-Dist: rich>=13.0.0
Requires-Dist: PyYAML>=6.0
Requires-Dist: GitPython>=3.1.0
Requires-Dist: requests>=2.31.0
Requires-Dist: ruff>=0.4.0
Provides-Extra: dev
Requires-Dist: pytest>=8.0.0; extra == "dev"
Requires-Dist: pytest-cov>=4.1.0; extra == "dev"
Requires-Dist: pytest-mock>=3.12.0; extra == "dev"
Provides-Extra: poker
Requires-Dist: websockets>=12.0; extra == "poker"
Dynamic: license-file
